glow/__init__.py
glow/actnorm.py
glow/conv.py
glow/coupling.py
glow/glow.py
glow/utils.py
pytorch_glow-0.0.1.dist-info/LICENSE
pytorch_glow-0.0.1.dist-info/METADATA
pytorch_glow-0.0.1.dist-info/WHEEL
pytorch_glow-0.0.1.dist-info/top_level.txt
pytorch_glow-0.0.1.dist-info/RECORD
